__suanpan__/__init__.py
__suanpan__/asyncio.py
__suanpan__/tensorflow.py
suanpan/__init__.py
suanpan/asyncio.py
suanpan/components.py
suanpan/g.py
suanpan/imports.py
suanpan/lazy_import.py
suanpan/log.py
suanpan/node_badge.py
suanpan/notebook.py
suanpan/objects.py
suanpan/path.py
suanpan/proxy.py
suanpan/run.py
suanpan/runtime.py
suanpan/service_registry.py
suanpan/simple_run.py
suanpan/version.py
suanpan/api/__init__.py
suanpan/api/app.py
suanpan/api/auth.py
suanpan/api/component.py
suanpan/api/oss.py
suanpan/api/pdb.py
suanpan/api/sio.py
suanpan/api/hardware/__init__.py
suanpan/api/hardware/app.py
suanpan/api/hardware/suanpan.py
suanpan/api/requests/__init__.py
suanpan/api/requests/affinity.py
suanpan/api/requests/host.py
suanpan/app/__init__.py
suanpan/app/arguments.py
suanpan/app/base.py
suanpan/app/docker.py
suanpan/app/loops.py
suanpan/app/message_handler.py
suanpan/app/spark.py
suanpan/app/stream.py
suanpan/app/modules/__init__.py
suanpan/app/modules/base.py
suanpan/app/modules/core.py
suanpan/app/modules/front.py
suanpan/app/modules/images.py
suanpan/app/modules/node.py
suanpan/app/modules/params.py
suanpan/app/modules/storage.py
suanpan/arguments/__init__.py
suanpan/arguments/auto.py
suanpan/debug/__init__.py
suanpan/debug/ab.py
suanpan/device/__init__.py
suanpan/device/base.py
suanpan/device/zmq.py
suanpan/docker/__init__.py
suanpan/docker/arguments.py
suanpan/dw/__init__.py
suanpan/dw/arguments.py
suanpan/dw/base.py
suanpan/dw/hive.py
suanpan/dw/mock.py
suanpan/dw/mysql.py
suanpan/dw/odps.py
suanpan/dw/postgres.py
suanpan/error/__init__.py
suanpan/error/api.py
suanpan/error/app.py
suanpan/error/arguments.py
suanpan/error/base.py
suanpan/error/component.py
suanpan/error/device.py
suanpan/error/graph.py
suanpan/error/imports.py
suanpan/error/interface.py
suanpan/error/model.py
suanpan/error/mq.py
suanpan/error/mstorage.py
suanpan/error/node.py
suanpan/error/proxy.py
suanpan/error/spark.py
suanpan/error/state.py
suanpan/error/stream.py
suanpan/error/tool.py
python_suanpan_no_stream-0.20.8.8.dist-info/METADATA
python_suanpan_no_stream-0.20.8.8.dist-info/WHEEL
python_suanpan_no_stream-0.20.8.8.dist-info/entry_points.txt
python_suanpan_no_stream-0.20.8.8.dist-info/top_level.txt
python_suanpan_no_stream-0.20.8.8.dist-info/RECORD
